intermag/__init__.py
intermag/__main__.py
intermag-0.0.1.dist-info/LICENSE
intermag-0.0.1.dist-info/METADATA
intermag-0.0.1.dist-info/WHEEL
intermag-0.0.1.dist-info/top_level.txt
intermag-0.0.1.dist-info/RECORD
