Metadata-Version: 2.1
Name: intermag
Version: 0.0.1
Summary: Python library to auto-download, manipulate, and process magnetic data from INTERMAGNET sites
Home-page: https://github.com/PowerBroker2/intermag
Download-URL: https://github.com/PowerBroker2/intermag/archive/0.0.1.tar.gz
Author: Power_Broker
Author-email: gitstuff2@gmail.com
Keywords: War Thunder
License-File: LICENSE
Requires-Dist: numpy
Requires-Dist: pandas
Requires-Dist: matplotlib
Requires-Dist: scipy
Requires-Dist: ppigrf
